paradeps/__init__.py
paradeps-0.1.1.dist-info/entry_points.txt
paradeps-0.1.1.dist-info/LICENSE.txt
paradeps-0.1.1.dist-info/WHEEL
paradeps-0.1.1.dist-info/METADATA
paradeps-0.1.1.dist-info/RECORD
