Metadata-Version: 2.1
Name: paradeps
Version: 0.1.1
Summary: Resolves dependencies into tiers suitable for parallel work
License: AGPL-3.0-only
Author: Lee Braiden
Author-email: leebraid@gmail.com
Requires-Python: >=3.10,<4.0
Classifier: License :: OSI Approved :: GNU Affero General Public License v3
Classifier: Programming Language :: Python :: 3
Classifier: Programming Language :: Python :: 3.10
